{"plans":{"2026-03-15":[{"id":1773538252105,"timeRange":["09:30","10:00"],"content":"打游戏","category":"娱乐","completed":true,"satisfaction":"100","accomplishment":"玩了一个小时瑞奇与叮当2"},{"id":1773510652431,"timeRange":["10:00","12:00"],"content":"写作业","category":"学习","completed":true,"satisfaction":"50","accomplishment":"作业没有写 整理了下周作业"},{"id":1773567025472,"timeRange":["17:30","18:00"],"content":"打游戏","description":"放开了玩","category":"娱乐","completed":true,"satisfaction":"100","accomplishment":"玩得还挺开心"},{"id":1773567052228,"timeRange":["18:30","20:00"],"content":"写作业","description":"写完周末作业","category":"学习","completed":true,"satisfaction":"100","accomplishment":"写完了周一要讲评的作业"},{"id":1773586007200,"timeRange":["22:30","23:30"],"content":"睡觉","description":"十点半准备入睡","category":"生活","completed":true,"satisfaction":0,"accomplishment":"没睡着 讨厌上班"}],"2026-03-16":[{"id":1773579431360,"timeRange":["09:00","10:00"],"content":"写作业","description":"把当天的作业写完","category":"学习","completed":true,"satisfaction":"30","accomplishment":"就写了一组选择题，在办公室关顾着聊天了。"},{"id":1773579473482,"timeRange":["14:30","16:00"],"content":"练胸","description":"练胸 重量组","category":"健身","completed":true,"satisfaction":"90","accomplishment":"除了卧推垃圾，其他还挺不错的啊"},{"id":1773656780824,"timeRange":["17:00","18:30"],"content":"写作业","description":"把当天的作业写完","category":"学习","completed":true,"satisfaction":"100","accomplishment":"这下真把作业写完了"},{"id":1773579504916,"timeRange":["18:00","19:30"],"content":"打游戏","description":"放开了玩","category":"娱乐","completed":true,"satisfaction":"100","accomplishment":"分开了玩了，挺不错"},{"id":1773579589075,"timeRange":["20:00","21:30"],"content":"学英语","description":"口语","category":"学习","completed":true,"satisfaction":"40","accomplishment":"emmm学了半个小时 不太习惯"},{"id":1773585930605,"timeRange":["22:30","23:30"],"content":"睡觉","description":"十点半准备入睡","category":"生活","completed":true,"satisfaction":0,"accomplishment":"没睡着"}],"2026-03-17":[{"id":1773669121626,"timeRange":["10:00","11:00"],"content":"写作业","description":"把当天的作业写完","category":"学习","completed":true,"satisfaction":"100","accomplishment":"今天作业写完啦 没有聊天哈哈 开心回家"},{"id":1773669153298,"timeRange":["15:00","16:30"],"content":"练背","description":"练背 重量组","category":"健身","completed":true,"satisfaction":"100","accomplishment":"嘎嘎猛"},{"id":1773669177766,"timeRange":["17:30","18:30"],"content":"羽毛球","description":"忙里偷闲 我要减脂","category":"健身","completed":true,"satisfaction":"100","accomplishment":"心率干上201了 爽了"},{"id":1773669282373,"timeRange":["19:00","21:00"],"content":"学英语","description":"晚自习看看能否学点英语？","category":"学习","completed":true,"satisfaction":"30","accomplishment":"英语没学，搞了周四学生小测，关顾着和学生聊天了"},{"id":1773669225148,"timeRange":["23:00","00:00"],"content":"睡觉","description":"十一点准备入睡","category":"生活","completed":true,"satisfaction":"80","accomplishment":"十一点半睡的 挺不错"}],"2026-03-18":[{"id":1773755672156,"timeRange":["09:00","10:00"],"content":"备课","description":"一定要认真备课，不要聊天","category":"学习","completed":true,"satisfaction":"100","accomplishment":"备课了 干活了"},{"id":1773755696573,"timeRange":["15:00","16:30"],"content":"练腿","description":"啊啊啊啊，有点抗拒啊","category":"健身","completed":false,"satisfaction":0,"accomplishment":""},{"id":1773755709254,"timeRange":["17:00","18:30"],"content":"打游戏","description":"放开了玩","category":"娱乐","completed":true,"satisfaction":"100","accomplishment":"放开了玩了，通过了瑞奇与叮当"},{"id":1773847783723,"timeRange":["18:30","21:00"],"content":"备课","description":"晚自习备课 改卷子","category":"学习","completed":false,"satisfaction":0,"accomplishment":""},{"id":1773755739939,"timeRange":["19:00","21:00"],"content":"学英语","description":"认真学习口语","category":"学习","completed":true,"satisfaction":"90","accomplishment":"认真学了"},{"id":1773755758256,"timeRange":["21:00","22:00"],"content":"查缺补漏","description":"看看有什么没有完成的","category":"学习","completed":true,"satisfaction":"100","accomplishment":"备课了"},{"id":1773755772804,"timeRange":["22:30","23:30"],"content":"睡觉","description":"十点半准备入睡","category":"生活","completed":true,"satisfaction":"50","accomplishment":"没睡"}],"2026-03-19":[{"id":1773847741698,"timeRange":["17:30","18:30"],"content":"羽毛球","description":"忙里偷闲 我要减脂","category":"健身","completed":true,"satisfaction":"100","accomplishment":"挺不错"}],"2026-03-20":[{"id":1773935492551,"timeRange":["14:00","16:00"],"content":"打游戏","description":"放开了玩","category":"娱乐","completed":true,"satisfaction":"100","accomplishment":"玩爽了"},{"id":1773935519869,"timeRange":["19:00","21:00"],"content":"打游戏","description":"放开了玩","category":"娱乐","completed":true,"satisfaction":"100","accomplishment":"开始新游戏 死亡搁浅"}],"2026-03-23":[{"id":1774185782480,"timeRange":["09:00","10:00"],"content":"备课","description":"一定要好好备课 不把活带回家","category":"学习","completed":true,"satisfaction":0,"accomplishment":"没备课 在学校干其他事了"},{"id":1774185797911,"timeRange":["15:00","16:30"],"content":"练胸","description":"练胸 重量组","category":"健身","completed":true,"satisfaction":"90","accomplishment":"卧推废物😭"},{"id":1774185821662,"timeRange":["17:00","18:00"],"content":"打游戏","description":"放开了玩","category":"娱乐","completed":true,"satisfaction":"100","accomplishment":"送快递了 挺开心"},{"id":1774185836365,"timeRange":["19:00","20:00"],"content":"学英语","description":"认真学习口语","category":"学习","completed":true,"satisfaction":"80","accomplishment":"应该是学不了英语了 得备课了"}],"2026-03-24":[{"id":1774271002436,"timeRange":["10:00","11:00"],"content":"备课","description":"一定要好好备课 不把活带回家","category":"学习","completed":true,"satisfaction":"90","accomplishment":"写了今天的作业"},{"id":1774271016733,"timeRange":["15:00","16:30"],"content":"练背","description":"练背 重量组","category":"健身","completed":true,"satisfaction":"100","accomplishment":"嘎嘎猛"},{"id":1774271028949,"timeRange":["17:30","18:30"],"content":"羽毛球","description":"忙里偷闲 我要减脂","category":"健身","completed":true,"satisfaction":"100","accomplishment":"燃尽了"},{"id":1774271076609,"timeRange":["18:30","21:00"],"content":"晚自习","description":"教学生读书","category":"学习","completed":true,"satisfaction":"30","accomplishment":"光顾着聊天了"}]},"summaries":{"2026-03-15":{"mood":"😐","text":"明天要上班了，有点小难过"},"2026-03-16":{"mood":"😊","text":"讨厌卧推，有点不开心，原地踏步一个月了"},"2026-03-17":{"mood":"😊","text":"练爽了，但是没学啥"},"2026-03-18":{"mood":"😐","text":"不喜欢今天 累"},"2026-03-19":{"mood":"😊","text":"还是挺不错的"},"2026-03-20":{"mood":"🤩","text":"爱上周五"},"2026-03-23":{"mood":"😊","text":"不喜欢上班"},"2026-03-24":{"mood":"🤩","text":"不错不错"}}}